intel_extension_for_transformers/libdnnl.so.3
intel_extension_for_transformers/qbits_py.cpython-38-x86_64-linux-gnu.so
intel_extension_for_transformers/libkernellibs.so
intel_extension_for_transformers/libglog.so.0.7.0
intel_extension_for_transformers/neural_engine_bin
intel_extension_for_transformers/libglog.so.1
intel_extension_for_transformers/neural_engine_py.cpython-38-x86_64-linux-gnu.so
intel_extension_for_transformers/libdnnl.so.3.2
intel_extension_for_transformers/libdnnl.so
intel_extension_for_transformers/libneural_engine.so
intel_extension_for_transformers/libglog.so
intel_extension_for_transformers/__init__.py
intel_extension_for_transformers/langchain/__init__.py
intel_extension_for_transformers/langchain/langchain_community/__init__.py
intel_extension_for_transformers/langchain/langchain_community/retrievers/child_parent_retriever.py
intel_extension_for_transformers/langchain/langchain_community/retrievers/bge_reranker.py
intel_extension_for_transformers/langchain/langchain_community/retrievers/__init__.py
intel_extension_for_transformers/langchain/langchain_community/embeddings/optimized_sentence_transformers.py
intel_extension_for_transformers/langchain/langchain_community/embeddings/embeddings.py
intel_extension_for_transformers/langchain/langchain_community/embeddings/optimized_instructor_embedding.py
intel_extension_for_transformers/langchain/langchain_community/embeddings/__init__.py
intel_extension_for_transformers/langchain/langchain_community/vectorstores/qdrant.py
intel_extension_for_transformers/langchain/langchain_community/vectorstores/chroma.py
intel_extension_for_transformers/langchain/langchain_community/vectorstores/__init__.py
intel_extension_for_transformers/llama_index/__init__.py
intel_extension_for_transformers/haystack/__init__.py
intel_extension_for_transformers/transformers/quantization.py
intel_extension_for_transformers/transformers/trainer.py
intel_extension_for_transformers-1.4.2.dist-info/top_level.txt
intel_extension_for_transformers-1.4.2.dist-info/LICENSE
intel_extension_for_transformers-1.4.2.dist-info/METADATA
intel_extension_for_transformers-1.4.2.dist-info/WHEEL
intel_extension_for_transformers-1.4.2.dist-info/entry_points.txt
intel_extension_for_transformers-1.4.2.dist-info/RECORD
