Metadata-Version: 2.1
Name: intel-extension-for-transformers
Version: 1.4.2
Summary: Repository of Intel® Intel Extension for Transformers
Home-page: https://github.com/intel/intel-extension-for-transformers
Author: Intel AIA/AIPC Team
Author-email: feng.tian@intel.com, haihao.shen@intel.com,hanwen.chang@intel.com, penghui.cheng@intel.com
License: Apache 2.0
Keywords: quantization,auto-tuning,post-training static quantization,post-training dynamic quantization,quantization-aware training,tuning strategy
Classifier: Intended Audience :: Science/Research
Classifier: Programming Language :: Python :: 3
Classifier: Topic :: Scientific/Engineering :: Artificial Intelligence
Classifier: License :: OSI Approved :: Apache Software License
Requires-Python: >=3.7.0
License-File: LICENSE
Requires-Dist: packaging
Requires-Dist: numpy
Requires-Dist: schema
Requires-Dist: pyyaml
Requires-Dist: neural_compressor
Requires-Dist: transformers
